<annotation>
	<folder>JPEGImages</folder>
	<filename>down_feather_sample2_99.jpg</filename>
	<path>E:\code\PythonProject\pytorch_object_detection\faster_rcnn\data_federn_daunen\JPEGImages\down_feather_sample2_99.jpg</path>
	<source>
		<database>Unknown</database>
	</source>
	<size>
		<width>640</width>
		<height>480</height>
		<depth>3</depth>
	</size>
	<segmented>0</segmented>
	<object>
		<name>federn</name>
		<pose>Unspecified</pose>
		<truncated>0</truncated>
		<difficult>0</difficult>
		<bndbox>
			<xmin>134</xmin>
			<ymin>181</ymin>
			<xmax>195</xmax>
			<ymax>262</ymax>
		</bndbox>
	</object>
	<object>
		<name>daunen</name>
		<pose>Unspecified</pose>
		<truncated>0</truncated>
		<difficult>0</difficult>
		<bndbox>
			<xmin>195</xmin>
			<ymin>91</ymin>
			<xmax>293</xmax>
			<ymax>159</ymax>
		</bndbox>
	</object>
	<object>
		<name>daunen</name>
		<pose>Unspecified</pose>
		<truncated>0</truncated>
		<difficult>0</difficult>
		<bndbox>
			<xmin>330</xmin>
			<ymin>26</ymin>
			<xmax>419</xmax>
			<ymax>128</ymax>
		</bndbox>
	</object>
	<object>
		<name>daunen</name>
		<pose>Unspecified</pose>
		<truncated>0</truncated>
		<difficult>0</difficult>
		<bndbox>
			<xmin>350</xmin>
			<ymin>164</ymin>
			<xmax>411</xmax>
			<ymax>215</ymax>
		</bndbox>
	</object>
	<object>
		<name>daunen</name>
		<pose>Unspecified</pose>
		<truncated>0</truncated>
		<difficult>0</difficult>
		<bndbox>
			<xmin>220</xmin>
			<ymin>265</ymin>
			<xmax>273</xmax>
			<ymax>327</ymax>
		</bndbox>
	</object>
	<object>
		<name>daunen</name>
		<pose>Unspecified</pose>
		<truncated>0</truncated>
		<difficult>0</difficult>
		<bndbox>
			<xmin>342</xmin>
			<ymin>243</ymin>
			<xmax>416</xmax>
			<ymax>316</ymax>
		</bndbox>
	</object>
	<object>
		<name>federn</name>
		<pose>Unspecified</pose>
		<truncated>0</truncated>
		<difficult>0</difficult>
		<bndbox>
			<xmin>426</xmin>
			<ymin>280</ymin>
			<xmax>569</xmax>
			<ymax>456</ymax>
		</bndbox>
	</object>
</annotation>
