<annotation>
	<folder>JPEGImages</folder>
	<filename>down_feather_sample2_57.jpg</filename>
	<path>E:\code\PythonProject\pytorch_object_detection\faster_rcnn\data_federn_daunen\JPEGImages\down_feather_sample2_57.jpg</path>
	<source>
		<database>Unknown</database>
	</source>
	<size>
		<width>640</width>
		<height>480</height>
		<depth>3</depth>
	</size>
	<segmented>0</segmented>
	<object>
		<name>federn</name>
		<pose>Unspecified</pose>
		<truncated>0</truncated>
		<difficult>0</difficult>
		<bndbox>
			<xmin>59</xmin>
			<ymin>135</ymin>
			<xmax>304</xmax>
			<ymax>330</ymax>
		</bndbox>
	</object>
	<object>
		<name>federn</name>
		<pose>Unspecified</pose>
		<truncated>0</truncated>
		<difficult>0</difficult>
		<bndbox>
			<xmin>288</xmin>
			<ymin>92</ymin>
			<xmax>383</xmax>
			<ymax>196</ymax>
		</bndbox>
	</object>
</annotation>
