<annotation>
	<folder>JPEGImages</folder>
	<filename>down_feather_sample2_46.jpg</filename>
	<path>E:\code\PythonProject\pytorch_object_detection\faster_rcnn\data_federn_daunen\JPEGImages\down_feather_sample2_46.jpg</path>
	<source>
		<database>Unknown</database>
	</source>
	<size>
		<width>640</width>
		<height>480</height>
		<depth>3</depth>
	</size>
	<segmented>0</segmented>
	<object>
		<name>federn</name>
		<pose>Unspecified</pose>
		<truncated>0</truncated>
		<difficult>0</difficult>
		<bndbox>
			<xmin>202</xmin>
			<ymin>37</ymin>
			<xmax>325</xmax>
			<ymax>145</ymax>
		</bndbox>
	</object>
	<object>
		<name>federn</name>
		<pose>Unspecified</pose>
		<truncated>0</truncated>
		<difficult>0</difficult>
		<bndbox>
			<xmin>200</xmin>
			<ymin>181</ymin>
			<xmax>313</xmax>
			<ymax>310</ymax>
		</bndbox>
	</object>
	<object>
		<name>federn</name>
		<pose>Unspecified</pose>
		<truncated>0</truncated>
		<difficult>0</difficult>
		<bndbox>
			<xmin>350</xmin>
			<ymin>114</ymin>
			<xmax>472</xmax>
			<ymax>261</ymax>
		</bndbox>
	</object>
</annotation>
