<annotation>
	<folder>JPEGImages</folder>
	<filename>IMG_E1285.jpg</filename>
	<path>E:\code\PythonProject\faster_rcnn\VOCdevkit\federn_daunen\JPEGImages\IMG_E1285.jpg</path>
	<source>
		<database>Unknown</database>
	</source>
	<size>
		<width>2369</width>
		<height>3602</height>
		<depth>3</depth>
	</size>
	<segmented>0</segmented>
	<object>
		<name>daunen</name>
		<pose>Unspecified</pose>
		<truncated>0</truncated>
		<difficult>0</difficult>
		<bndbox>
			<xmin>945</xmin>
			<ymin>1751</ymin>
			<xmax>1553</xmax>
			<ymax>2178</ymax>
		</bndbox>
	</object>
</annotation>
